shuttlet_sora2_mcp/__init__.py
shuttlet_sora2_mcp-0.1.0.dist-info/WHEEL
shuttlet_sora2_mcp-0.1.0.dist-info/entry_points.txt
shuttlet_sora2_mcp-0.1.0.dist-info/METADATA
shuttlet_sora2_mcp-0.1.0.dist-info/RECORD
