Metadata-Version: 2.3
Name: shuttlet_sora2_mcp
Version: 0.1.0
Summary: Sora2 MCP Server - 基于 Sora2 视频模型的 MCP 服务器实现
Author: entelin
Author-email: entelin <entelin@tencent.com>
Requires-Dist: mcp[cli]>=1.25.0
Requires-Dist: requests>=2.32.5
Requires-Python: >=3.13
